<?xml version="1.0" encoding="utf-8" ?>
<dwsync>
<file name="admin-bar.js" server="ftp.pixelab.com.au/www/gimmegolfdeals/" local="130382750991803634" remote="130382730600000000" Dst="2" />
<file name="admin-bar.min.js" server="ftp.pixelab.com.au/www/gimmegolfdeals/" local="130382750991863658" remote="130382730600000000" Dst="2" />
<file name="autosave.min.js" server="ftp.pixelab.com.au/www/gimmegolfdeals/" local="130382750991993656" remote="130382730600000000" Dst="2" />
<file name="autosave.js" server="ftp.pixelab.com.au/www/gimmegolfdeals/" local="130382750991923131" remote="130382730600000000" Dst="2" />
<file name="backbone.min.js" server="ftp.pixelab.com.au/www/gimmegolfdeals/" local="130382750992093692" remote="130382730600000000" Dst="2" />
<file name="colorpicker.js" server="ftp.pixelab.com.au/www/gimmegolfdeals/" local="130382750992433657" remote="130382730600000000" Dst="2" />
<file name="colorpicker.min.js" server="ftp.pixelab.com.au/www/gimmegolfdeals/" local="130382750992503728" remote="130382730600000000" Dst="2" />
<file name="comment-reply.js" server="ftp.pixelab.com.au/www/gimmegolfdeals/" local="130382750992523723" remote="130382730600000000" Dst="2" />
<file name="comment-reply.min.js" server="ftp.pixelab.com.au/www/gimmegolfdeals/" local="130382750992663691" remote="130382730600000000" Dst="2" />
<file name="customize-base.js" server="ftp.pixelab.com.au/www/gimmegolfdeals/" local="130382750992823481" remote="130382730600000000" Dst="2" />
<file name="customize-base.min.js" server="ftp.pixelab.com.au/www/gimmegolfdeals/" local="130382750992893464" remote="130382730600000000" Dst="2" />
<file name="customize-loader.js" server="ftp.pixelab.com.au/www/gimmegolfdeals/" local="130382750992933685" remote="130382730600000000" Dst="2" />
<file name="customize-loader.min.js" server="ftp.pixelab.com.au/www/gimmegolfdeals/" local="130382750992953745" remote="130382730600000000" Dst="2" />
<file name="customize-preview.js" server="ftp.pixelab.com.au/www/gimmegolfdeals/" local="130382750993003521" remote="130382730600000000" Dst="2" />
<file name="customize-preview.min.js" server="ftp.pixelab.com.au/www/gimmegolfdeals/" local="130382750993033194" remote="130382730600000000" Dst="2" />
<file name="heartbeat.js" server="ftp.pixelab.com.au/www/gimmegolfdeals/" local="130382750993073199" remote="130382730600000000" Dst="2" />
<file name="heartbeat.min.js" server="ftp.pixelab.com.au/www/gimmegolfdeals/" local="130382750993113709" remote="130382730600000000" Dst="2" />
<file name="hoverIntent.js" server="ftp.pixelab.com.au/www/gimmegolfdeals/" local="130382750993153753" remote="130382730600000000" Dst="2" />
<file name="hoverIntent.min.js" server="ftp.pixelab.com.au/www/gimmegolfdeals/" local="130382750993183741" remote="130382730600000000" Dst="2" />
<file name="json2.js" server="ftp.pixelab.com.au/www/gimmegolfdeals/" local="130382750996313916" remote="130382730600000000" Dst="2" />
<file name="json2.min.js" server="ftp.pixelab.com.au/www/gimmegolfdeals/" local="130382750996363734" remote="130382730600000000" Dst="2" />
<file name="mce-view.js" server="ftp.pixelab.com.au/www/gimmegolfdeals/" local="130382750996393637" remote="130382730600000000" Dst="2" />
<file name="mce-view.min.js" server="ftp.pixelab.com.au/www/gimmegolfdeals/" local="130382750996433581" remote="130382730600000000" Dst="2" />
<file name="media-editor.min.js" server="ftp.pixelab.com.au/www/gimmegolfdeals/" local="130382750996533591" remote="130382730600000000" Dst="2" />
<file name="media-editor.js" server="ftp.pixelab.com.au/www/gimmegolfdeals/" local="130382750996483592" remote="130382730600000000" Dst="2" />
<file name="media-models.js" server="ftp.pixelab.com.au/www/gimmegolfdeals/" local="130382750996593398" remote="130382730600000000" Dst="2" />
<file name="media-models.min.js" server="ftp.pixelab.com.au/www/gimmegolfdeals/" local="130382750996653622" remote="130382730600000000" Dst="2" />
<file name="media-views.js" server="ftp.pixelab.com.au/www/gimmegolfdeals/" local="130382750996803596" remote="130382730600000000" Dst="2" />
<file name="media-views.min.js" server="ftp.pixelab.com.au/www/gimmegolfdeals/" local="130382750996943611" remote="130382730600000000" Dst="2" />
<file name="quicktags.js" server="ftp.pixelab.com.au/www/gimmegolfdeals/" local="130382750998013707" remote="130382730600000000" Dst="2" />
<file name="quicktags.min.js" server="ftp.pixelab.com.au/www/gimmegolfdeals/" local="130382750998073684" remote="130382730600000000" Dst="2" />
<file name="shortcode.js" server="ftp.pixelab.com.au/www/gimmegolfdeals/" local="130382750998113843" remote="130382730600000000" Dst="2" />
<file name="swfobject.js" server="ftp.pixelab.com.au/www/gimmegolfdeals/" local="130382750998223492" remote="130382730600000000" Dst="2" />
<file name="shortcode.min.js" server="ftp.pixelab.com.au/www/gimmegolfdeals/" local="130382750998153714" remote="130382730600000000" Dst="2" />
<file name="tw-sack.js" server="ftp.pixelab.com.au/www/gimmegolfdeals/" local="130382751003873852" remote="130382731200000000" Dst="2" />
<file name="tw-sack.min.js" server="ftp.pixelab.com.au/www/gimmegolfdeals/" local="130382751003914042" remote="130382731200000000" Dst="2" />
<file name="utils.js" server="ftp.pixelab.com.au/www/gimmegolfdeals/" local="130382751004044364" remote="130382731200000000" Dst="2" />
<file name="underscore.min.js" server="ftp.pixelab.com.au/www/gimmegolfdeals/" local="130382751004004027" remote="130382731200000000" Dst="2" />
<file name="utils.min.js" server="ftp.pixelab.com.au/www/gimmegolfdeals/" local="130382751004073833" remote="130382731200000000" Dst="2" />
<file name="wp-ajax-response.min.js" server="ftp.pixelab.com.au/www/gimmegolfdeals/" local="130382751004144092" remote="130382731200000000" Dst="2" />
<file name="wp-ajax-response.js" server="ftp.pixelab.com.au/www/gimmegolfdeals/" local="130382751004114350" remote="130382731200000000" Dst="2" />
<file name="wp-auth-check.js" server="ftp.pixelab.com.au/www/gimmegolfdeals/" local="130382751004174385" remote="130382731200000000" Dst="2" />
<file name="wp-backbone.min.js" server="ftp.pixelab.com.au/www/gimmegolfdeals/" local="130382751004284057" remote="130382731200000000" Dst="2" />
<file name="wp-backbone.js" server="ftp.pixelab.com.au/www/gimmegolfdeals/" local="130382751004234435" remote="130382731200000000" Dst="2" />
<file name="wp-auth-check.min.js" server="ftp.pixelab.com.au/www/gimmegolfdeals/" local="130382751004194380" remote="130382731200000000" Dst="2" />
<file name="wp-list-revisions.js" server="ftp.pixelab.com.au/www/gimmegolfdeals/" local="130382751004304437" remote="130382731200000000" Dst="2" />
<file name="wp-list-revisions.min.js" server="ftp.pixelab.com.au/www/gimmegolfdeals/" local="130382751004324393" remote="130382731200000000" Dst="2" />
<file name="wp-lists.js" server="ftp.pixelab.com.au/www/gimmegolfdeals/" local="130382751004374204" remote="130382731200000000" Dst="2" />
<file name="wp-lists.min.js" server="ftp.pixelab.com.au/www/gimmegolfdeals/" local="130382751004424080" remote="130382731200000000" Dst="2" />
<file name="wp-pointer.js" server="ftp.pixelab.com.au/www/gimmegolfdeals/" local="130382751004464046" remote="130382731200000000" Dst="2" />
<file name="wp-pointer.min.js" server="ftp.pixelab.com.au/www/gimmegolfdeals/" local="130382751004684407" remote="130382731200000000" Dst="2" />
<file name="wp-util.js" server="ftp.pixelab.com.au/www/gimmegolfdeals/" local="130382751004704379" remote="130382731200000000" Dst="2" />
<file name="wp-util.min.js" server="ftp.pixelab.com.au/www/gimmegolfdeals/" local="130382751004734048" remote="130382731200000000" Dst="2" />
<file name="wplink.js" server="ftp.pixelab.com.au/www/gimmegolfdeals/" local="130382751004794880" remote="130382731200000000" Dst="2" />
<file name="wplink.min.js" server="ftp.pixelab.com.au/www/gimmegolfdeals/" local="130382751004844289" remote="130382731200000000" Dst="2" />
<file name="zxcvbn-async.js" server="ftp.pixelab.com.au/www/gimmegolfdeals/" local="130382751004854445" remote="130382731200000000" Dst="2" />
<file name="zxcvbn-async.min.js" server="ftp.pixelab.com.au/www/gimmegolfdeals/" local="130382751004874440" remote="130382731200000000" Dst="2" />
<file name="zxcvbn.min.js" server="ftp.pixelab.com.au/www/gimmegolfdeals/" local="130382751005123896" remote="130382731200000000" Dst="2" />
</dwsync>