<?xml version="1.0" encoding="utf-8" ?>
<dwsync>
<file name="about.php" server="ftp.pixelab.com.au/www/gimmegolfdeals/" local="130382750930919617" remote="130382728800000000" Dst="2" />
<file name="credits.php" server="ftp.pixelab.com.au/www/gimmegolfdeals/" local="130382750930960100" remote="130382728800000000" Dst="2" />
<file name="admin.php" server="ftp.pixelab.com.au/www/gimmegolfdeals/" local="130382750930940148" remote="130382728800000000" Dst="2" />
<file name="freedoms.php" server="ftp.pixelab.com.au/www/gimmegolfdeals/" local="130382750930980099" remote="130382728800000000" Dst="2" />
<file name="index.php" server="ftp.pixelab.com.au/www/gimmegolfdeals/" local="130382750930999982" remote="130382728800000000" Dst="2" />
<file name="menu.php" server="ftp.pixelab.com.au/www/gimmegolfdeals/" local="130382750931020100" remote="130382728800000000" Dst="2" />
<file name="profile.php" server="ftp.pixelab.com.au/www/gimmegolfdeals/" local="130382750931049631" remote="130382728800000000" Dst="2" />
<file name="user-edit.php" server="ftp.pixelab.com.au/www/gimmegolfdeals/" local="130382750931069630" remote="130382728800000000" Dst="2" />
</dwsync>